ruamel/yaml/convert/__init__.py
ruamel/yaml/convert/csv_yaml.py
ruamel/yaml/convert/html_yaml.py
ruamel/yaml/convert/syncjson.py
ruamel.yaml.convert-0.3.2.dist-info/DESCRIPTION.rst
ruamel.yaml.convert-0.3.2.dist-info/LICENSE.txt
ruamel.yaml.convert-0.3.2.dist-info/METADATA
ruamel.yaml.convert-0.3.2.dist-info/RECORD
ruamel.yaml.convert-0.3.2.dist-info/WHEEL
ruamel.yaml.convert-0.3.2.dist-info/metadata.json
ruamel.yaml.convert-0.3.2.dist-info/namespace_packages.txt
ruamel.yaml.convert-0.3.2.dist-info/top_level.txt
