Metadata-Version: 1.1
Name: ruamel.yaml.convert
Version: 0.3.2
Summary: data format conversion routines to/from YAML
Home-page: https://bitbucket.org/ruamel/yaml.convert
Author: Anthon van der Neut
Author-email: a.van.der.neut@ruamel.eu
License: MIT license
Platform: UNKNOWN
Classifier: Development Status :: 3 - Alpha
Classifier: Intended Audience :: Developers
Classifier: License :: OSI Approved :: MIT License
Classifier: Operating System :: OS Independent
Classifier: Programming Language :: Python
